{
    "game_id": "matchgame-8cc332a6-ca9a-4a46-9985-25f0ca2e715e",
    "match_id": "match-b5ad861a-3cd5-d647-816b-0a47244fbf67",
    "tournament_id": "tournament-9d67219d-87d7-8441-ab9a-9ff9ca49a85d",
    "tournament_type": "owl",
    "season_id": "2019",
    "game_number": 2,
    "map_id": "0x08000000000001DB",
    "map_type": "ASSAULT",
    "esports_tournament_id": 5081,
    "esports_match_id": 21461,
    "teams": [
        {
            "esports_team_id": 4403,
            "stats": [
                {
                    "name": "deaths",
                    "value": 45,
                    "id": "0x086000000000002A"
                }
            ],
            "players": [
                {
                    "esports_player_id": 8236,
                    "stats": [
                        {
                            "name": "damage",
                            "value": 16335.314975351095,
                            "id": "0x08600000000001BF"
                        },
                        {
                            "name": "deaths",
                            "value": 7,
                            "id": "0x086000000000002A"
                        },
                        {
                            "name": "eliminations",
                            "value": 20,
                            "id": "0x086000000000001F"
                        },
                        {
                            "name": "healing",
                            "value": 182.74964886903763,
                            "id": "0x08600000000001C1"
                        }
                    ],
                    "heroes": [
                        {
                            "hero_id": "0x02E0000000000002",
                            "name": "reaper",
                            "stats": [
                                {
                                    "name": "damage",
                                    "value": 797.2969435453415,
                                    "id": "0x08600000000001BF"
                                },
                                {
                                    "name": "deaths",
                                    "value": 1,
                                    "id": "0x086000000000002A"
                                },
                                {
                                    "name": "eliminations",
                                    "value": 3,
                                    "id": "0x086000000000001F"
                                },
                                {
                                    "name": "healing",
                                    "value": 182.74964886903763,
                                    "id": "0x08600000000001C1"
                                }
                            ]
                        },
                        {
                            "hero_id": "0x02E000000000000A",
                            "name": "widowmaker",
                            "stats": [
                                {
                                    "name": "damage",
                                    "value": 3792.40387737751,
                                    "id": "0x08600000000001BF"
                                },
                                {
                                    "name": "deaths",
                                    "value": 1,
                                    "id": "0x086000000000002A"
                                },
                                {
                                    "name": "eliminations",
                                    "value": 5,
                                    "id": "0x086000000000001F"
                                }
                            ]
                        },
                        {
                            "hero_id": "0x02E0000000000068",
                            "name": "zarya",
                            "stats": [
                                {
                                    "name": "damage",
                                    "value": 8548.553006350994,
                                    "id": "0x08600000000001BF"
                                },
                                {
                                    "name": "deaths",
                                    "value": 4,
                                    "id": "0x086000000000002A"
                                },
                                {
                                    "name": "eliminations",
                                    "value": 6,
                                    "id": "0x086000000000001F"
                                }
                            ]
                        },
                        {
                            "hero_id": "0x02E000000000007A",
                            "name": "dva",
                            "stats": [
                                {
                                    "name": "damage",
                                    "value": 3103.1702150404453,
                                    "id": "0x08600000000001BF"
                                },
                                {
                                    "name": "deaths",
                                    "value": 1,
                                    "id": "0x086000000000002A"
                                },
                                {
                                    "name": "eliminations",
                                    "value": 5,
                                    "id": "0x086000000000001F"
                                }
                            ]
                        },
                        {
                            "hero_id": "0x02E000000000012F",
                            "name": "doomfist",
                            "stats": [
                                {
                                    "name": "damage",
                                    "value": 93.8909330368042,
                                    "id": "0x08600000000001BF"
                                },
                                {
                                    "name": "eliminations",
                                    "value": 1,
                                    "id": "0x086000000000001F"
                                }
                            ]
                        }
                    ]
                },
                {
                    "esports_player_id": 4654,
                    "stats": [
                        {
                            "name": "damage",
                            "value": 13258.980644106865,
                            "id": "0x08600000000001BF"
                        },
                        {
                            "name": "deaths",
                            "value": 9,
                            "id": "0x086000000000002A"
                        },
                        {
                            "name": "eliminations",
                            "value": 28,
                            "id": "0x086000000000001F"
                        },
                        {
                            "name": "healing",
                            "value": 7737.032827138901,
                            "id": "0x08600000000001C1"
                        }
                    ],
                    "heroes": [
                        {
                            "hero_id": "0x02E0000000000005",
                            "name": "hanzo",
                            "stats": [
                                {
                                    "name": "damage",
                                    "value": 4906.216045260429,
                                    "id": "0x08600000000001BF"
                                },
                                {
                                    "name": "deaths",
                                    "value": 2,
                                    "id": "0x086000000000002A"
                                },
                                {
                                    "name": "eliminations",
                                    "value": 12,
                                    "id": "0x086000000000001F"
                                }
                            ]
                        },
                        {
                            "hero_id": "0x02E0000000000195",
                            "name": "brigitte",
                            "stats": [
                                {
                                    "name": "damage",
                                    "value": 7711.964214324951,
                                    "id": "0x08600000000001BF"
                                },
                                {
                                    "name": "deaths",
                                    "value": 6,
                                    "id": "0x086000000000002A"
                                },
                                {
                                    "name": "eliminations",
                                    "value": 16,
                                    "id": "0x086000000000001F"
                                },
                                {
                                    "name": "healing",
                                    "value": 7737.032827138901,
                                    "id": "0x08600000000001C1"
                                }
                            ]
                        },
                        {
                            "hero_id": "0x02E000000000000A",
                            "name": "widowmaker",
                            "stats": [
                                {
                                    "name": "damage",
                                    "value": 640.8003845214844,
                                    "id": "0x08600000000001BF"
                                },
                                {
                                    "name": "deaths",
                                    "value": 1,
                                    "id": "0x086000000000002A"
                                }
                            ]
                        }
                    ]
                },
                {
                    "esports_player_id": 4093,
                    "stats": [
                        {
                            "name": "damage",
                            "value": 12197.992617368698,
                            "id": "0x08600000000001BF"
                        },
                        {
                            "name": "deaths",
                            "value": 11,
                            "id": "0x086000000000002A"
                        },
                        {
                            "name": "eliminations",
                            "value": 19,
                            "id": "0x086000000000001F"
                        }
                    ],
                    "heroes": [
                        {
                            "hero_id": "0x02E000000000013E",
                            "name": "orisa",
                            "stats": [
                                {
                                    "name": "damage",
                                    "value": 996.1118469238281,
                                    "id": "0x08600000000001BF"
                                },
                                {
                                    "name": "deaths",
                                    "value": 1,
                                    "id": "0x086000000000002A"
                                }
                            ]
                        },
                        {
                            "hero_id": "0x02E0000000000007",
                            "name": "reinhardt",
                            "stats": [
                                {
                                    "name": "damage",
                                    "value": 2443.76788520813,
                                    "id": "0x08600000000001BF"
                                },
                                {
                                    "name": "deaths",
                                    "value": 1,
                                    "id": "0x086000000000002A"
                                },
                                {
                                    "name": "eliminations",
                                    "value": 3,
                                    "id": "0x086000000000001F"
                                }
                            ]
                        },
                        {
                            "hero_id": "0x02E00000000001CA",
                            "name": "wreckingball",
                            "stats": [
                                {
                                    "name": "damage",
                                    "value": 3556.522523880005,
                                    "id": "0x08600000000001BF"
                                },
                                {
                                    "name": "deaths",
                                    "value": 1,
                                    "id": "0x086000000000002A"
                                },
                                {
                                    "name": "eliminations",
                                    "value": 10,
                                    "id": "0x086000000000001F"
                                }
                            ]
                        },
                        {
                            "hero_id": "0x02E0000000000009",
                            "name": "winston",
                            "stats": [
                                {
                                    "name": "damage",
                                    "value": 5201.590361356735,
                                    "id": "0x08600000000001BF"
                                },
                                {
                                    "name": "deaths",
                                    "value": 8,
                                    "id": "0x086000000000002A"
                                },
                                {
                                    "name": "eliminations",
                                    "value": 6,
                                    "id": "0x086000000000001F"
                                }
                            ]
                        }
                    ]
                },
                {
                    "esports_player_id": 4099,
                    "stats": [
                        {
                            "name": "damage",
                            "value": 14962.45558667183,
                            "id": "0x08600000000001BF"
                        },
                        {
                            "name": "deaths",
                            "value": 6,
                            "id": "0x086000000000002A"
                        },
                        {
                            "name": "eliminations",
                            "value": 20,
                            "id": "0x086000000000001F"
                        },
                        {
                            "name": "healing",
                            "value": 263.99998474121094,
                            "id": "0x08600000000001C1"
                        }
                    ],
                    "heroes": [
                        {
                            "hero_id": "0x02E0000000000007",
                            "name": "reinhardt",
                            "stats": []
                        },
                        {
                            "hero_id": "0x02E000000000007A",
                            "name": "dva",
                            "stats": [
                                {
                                    "name": "damage",
                                    "value": 4201.6363751888275,
                                    "id": "0x08600000000001BF"
                                },
                                {
                                    "name": "deaths",
                                    "value": 1,
                                    "id": "0x086000000000002A"
                                },
                                {
                                    "name": "eliminations",
                                    "value": 5,
                                    "id": "0x086000000000001F"
                                }
                            ]
                        },
                        {
                            "hero_id": "0x02E000000000012E",
                            "name": "sombra",
                            "stats": [
                                {
                                    "name": "damage",
                                    "value": 10760.819211483002,
                                    "id": "0x08600000000001BF"
                                },
                                {
                                    "name": "deaths",
                                    "value": 5,
                                    "id": "0x086000000000002A"
                                },
                                {
                                    "name": "eliminations",
                                    "value": 15,
                                    "id": "0x086000000000001F"
                                },
                                {
                                    "name": "healing",
                                    "value": 263.99998474121094,
                                    "id": "0x08600000000001C1"
                                }
                            ]
                        }
                    ]
                },
                {
                    "esports_player_id": 4653,
                    "stats": [
                        {
                            "name": "damage",
                            "value": 14947.23870420456,
                            "id": "0x08600000000001BF"
                        },
                        {
                            "name": "deaths",
                            "value": 7,
                            "id": "0x086000000000002A"
                        },
                        {
                            "name": "eliminations",
                            "value": 25,
                            "id": "0x086000000000001F"
                        },
                        {
                            "name": "healing",
                            "value": 9138.467267990112,
                            "id": "0x08600000000001C1"
                        }
                    ],
                    "heroes": [
                        {
                            "hero_id": "0x02E000000000013B",
                            "name": "ana",
                            "stats": [
                                {
                                    "name": "damage",
                                    "value": 6156.121890544891,
                                    "id": "0x08600000000001BF"
                                },
                                {
                                    "name": "deaths",
                                    "value": 5,
                                    "id": "0x086000000000002A"
                                },
                                {
                                    "name": "eliminations",
                                    "value": 12,
                                    "id": "0x086000000000001F"
                                },
                                {
                                    "name": "healing",
                                    "value": 5683.306715130806,
                                    "id": "0x08600000000001C1"
                                }
                            ]
                        },
                        {
                            "hero_id": "0x02E0000000000020",
                            "name": "zenyatta",
                            "stats": [
                                {
                                    "name": "damage",
                                    "value": 8791.116813659668,
                                    "id": "0x08600000000001BF"
                                },
                                {
                                    "name": "deaths",
                                    "value": 2,
                                    "id": "0x086000000000002A"
                                },
                                {
                                    "name": "eliminations",
                                    "value": 13,
                                    "id": "0x086000000000001F"
                                },
                                {
                                    "name": "healing",
                                    "value": 3455.1605528593063,
                                    "id": "0x08600000000001C1"
                                }
                            ]
                        }
                    ]
                },
                {
                    "esports_player_id": 4841,
                    "stats": [
                        {
                            "name": "damage",
                            "value": 8653.90200996399,
                            "id": "0x08600000000001BF"
                        },
                        {
                            "name": "deaths",
                            "value": 5,
                            "id": "0x086000000000002A"
                        },
                        {
                            "name": "eliminations",
                            "value": 18,
                            "id": "0x086000000000001F"
                        },
                        {
                            "name": "healing",
                            "value": 9390.90062713623,
                            "id": "0x08600000000001C1"
                        }
                    ],
                    "heroes": [
                        {
                            "hero_id": "0x02E0000000000079",
                            "name": "lucio",
                            "stats": [
                                {
                                    "name": "damage",
                                    "value": 8653.90200996399,
                                    "id": "0x08600000000001BF"
                                },
                                {
                                    "name": "deaths",
                                    "value": 4,
                                    "id": "0x086000000000002A"
                                },
                                {
                                    "name": "eliminations",
                                    "value": 18,
                                    "id": "0x086000000000001F"
                                },
                                {
                                    "name": "healing",
                                    "value": 6152.243846654892,
                                    "id": "0x08600000000001C1"
                                }
                            ]
                        },
                        {
                            "hero_id": "0x02E0000000000004",
                            "name": "mercy",
                            "stats": [
                                {
                                    "name": "deaths",
                                    "value": 1,
                                    "id": "0x086000000000002A"
                                },
                                {
                                    "name": "healing",
                                    "value": 3238.6567804813385,
                                    "id": "0x08600000000001C1"
                                }
                            ]
                        }
                    ]
                }
            ]
        },
        {
            "esports_team_id": 4407,
            "stats": [
                {
                    "name": "deaths",
                    "value": 46,
                    "id": "0x086000000000002A"
                }
            ],
            "players": [
                {
                    "esports_player_id": 4640,
                    "stats": [
                        {
                            "name": "damage",
                            "value": 15670.633879810572,
                            "id": "0x08600000000001BF"
                        },
                        {
                            "name": "deaths",
                            "value": 7,
                            "id": "0x086000000000002A"
                        },
                        {
                            "name": "eliminations",
                            "value": 22,
                            "id": "0x086000000000001F"
                        }
                    ],
                    "heroes": [
                        {
                            "hero_id": "0x02E0000000000005",
                            "name": "hanzo",
                            "stats": [
                                {
                                    "name": "damage",
                                    "value": 3548.5420704483986,
                                    "id": "0x08600000000001BF"
                                },
                                {
                                    "name": "eliminations",
                                    "value": 3,
                                    "id": "0x086000000000001F"
                                }
                            ]
                        },
                        {
                            "hero_id": "0x02E000000000007A",
                            "name": "dva",
                            "stats": [
                                {
                                    "name": "damage",
                                    "value": 5529.445374161005,
                                    "id": "0x08600000000001BF"
                                },
                                {
                                    "name": "deaths",
                                    "value": 5,
                                    "id": "0x086000000000002A"
                                },
                                {
                                    "name": "eliminations",
                                    "value": 11,
                                    "id": "0x086000000000001F"
                                }
                            ]
                        },
                        {
                            "hero_id": "0x02E0000000000068",
                            "name": "zarya",
                            "stats": [
                                {
                                    "name": "damage",
                                    "value": 6592.646435201168,
                                    "id": "0x08600000000001BF"
                                },
                                {
                                    "name": "deaths",
                                    "value": 2,
                                    "id": "0x086000000000002A"
                                },
                                {
                                    "name": "eliminations",
                                    "value": 8,
                                    "id": "0x086000000000001F"
                                }
                            ]
                        },
                        {
                            "hero_id": "0x02E0000000000008",
                            "name": "pharah",
                            "stats": []
                        }
                    ]
                },
                {
                    "esports_player_id": 8706,
                    "stats": [
                        {
                            "name": "damage",
                            "value": 6900.252163887024,
                            "id": "0x08600000000001BF"
                        },
                        {
                            "name": "deaths",
                            "value": 7,
                            "id": "0x086000000000002A"
                        },
                        {
                            "name": "eliminations",
                            "value": 13,
                            "id": "0x086000000000001F"
                        },
                        {
                            "name": "healing",
                            "value": 8330.127076864243,
                            "id": "0x08600000000001C1"
                        }
                    ],
                    "heroes": [
                        {
                            "hero_id": "0x02E0000000000079",
                            "name": "lucio",
                            "stats": [
                                {
                                    "name": "damage",
                                    "value": 6860.252163887024,
                                    "id": "0x08600000000001BF"
                                },
                                {
                                    "name": "deaths",
                                    "value": 5,
                                    "id": "0x086000000000002A"
                                },
                                {
                                    "name": "eliminations",
                                    "value": 12,
                                    "id": "0x086000000000001F"
                                },
                                {
                                    "name": "healing",
                                    "value": 4934.870646715164,
                                    "id": "0x08600000000001C1"
                                }
                            ]
                        },
                        {
                            "hero_id": "0x02E0000000000004",
                            "name": "mercy",
                            "stats": [
                                {
                                    "name": "damage",
                                    "value": 40,
                                    "id": "0x08600000000001BF"
                                },
                                {
                                    "name": "deaths",
                                    "value": 2,
                                    "id": "0x086000000000002A"
                                },
                                {
                                    "name": "eliminations",
                                    "value": 1,
                                    "id": "0x086000000000001F"
                                },
                                {
                                    "name": "healing",
                                    "value": 3395.2564301490784,
                                    "id": "0x08600000000001C1"
                                }
                            ]
                        }
                    ]
                },
                {
                    "esports_player_id": 4664,
                    "stats": [
                        {
                            "name": "damage",
                            "value": 12538.933837771416,
                            "id": "0x08600000000001BF"
                        },
                        {
                            "name": "deaths",
                            "value": 7,
                            "id": "0x086000000000002A"
                        },
                        {
                            "name": "eliminations",
                            "value": 18,
                            "id": "0x086000000000001F"
                        },
                        {
                            "name": "healing",
                            "value": 10638.2936065197,
                            "id": "0x08600000000001C1"
                        }
                    ],
                    "heroes": [
                        {
                            "hero_id": "0x02E000000000013B",
                            "name": "ana",
                            "stats": [
                                {
                                    "name": "damage",
                                    "value": 7169.419828414917,
                                    "id": "0x08600000000001BF"
                                },
                                {
                                    "name": "deaths",
                                    "value": 2,
                                    "id": "0x086000000000002A"
                                },
                                {
                                    "name": "eliminations",
                                    "value": 10,
                                    "id": "0x086000000000001F"
                                },
                                {
                                    "name": "healing",
                                    "value": 5697.988723158836,
                                    "id": "0x08600000000001C1"
                                }
                            ]
                        },
                        {
                            "hero_id": "0x02E0000000000040",
                            "name": "roadhog",
                            "stats": [
                                {
                                    "name": "damage",
                                    "value": 1797.2098639011383,
                                    "id": "0x08600000000001BF"
                                },
                                {
                                    "name": "deaths",
                                    "value": 1,
                                    "id": "0x086000000000002A"
                                },
                                {
                                    "name": "eliminations",
                                    "value": 1,
                                    "id": "0x086000000000001F"
                                },
                                {
                                    "name": "healing",
                                    "value": 327.6999282836914,
                                    "id": "0x08600000000001C1"
                                }
                            ]
                        },
                        {
                            "hero_id": "0x02E00000000001A2",
                            "name": "moira",
                            "stats": [
                                {
                                    "name": "damage",
                                    "value": 906.2798610925674,
                                    "id": "0x08600000000001BF"
                                },
                                {
                                    "name": "deaths",
                                    "value": 1,
                                    "id": "0x086000000000002A"
                                },
                                {
                                    "name": "eliminations",
                                    "value": 2,
                                    "id": "0x086000000000001F"
                                },
                                {
                                    "name": "healing",
                                    "value": 2134.587399959564,
                                    "id": "0x08600000000001C1"
                                }
                            ]
                        },
                        {
                            "hero_id": "0x02E0000000000020",
                            "name": "zenyatta",
                            "stats": [
                                {
                                    "name": "damage",
                                    "value": 2666.024284362793,
                                    "id": "0x08600000000001BF"
                                },
                                {
                                    "name": "deaths",
                                    "value": 3,
                                    "id": "0x086000000000002A"
                                },
                                {
                                    "name": "eliminations",
                                    "value": 5,
                                    "id": "0x086000000000001F"
                                },
                                {
                                    "name": "healing",
                                    "value": 2478.017555117607,
                                    "id": "0x08600000000001C1"
                                }
                            ]
                        }
                    ]
                },
                {
                    "esports_player_id": 4636,
                    "stats": [
                        {
                            "name": "damage",
                            "value": 14120.67278599739,
                            "id": "0x08600000000001BF"
                        },
                        {
                            "name": "deaths",
                            "value": 8,
                            "id": "0x086000000000002A"
                        },
                        {
                            "name": "eliminations",
                            "value": 27,
                            "id": "0x086000000000001F"
                        }
                    ],
                    "heroes": [
                        {
                            "hero_id": "0x02E0000000000009",
                            "name": "winston",
                            "stats": [
                                {
                                    "name": "damage",
                                    "value": 9147.29706120491,
                                    "id": "0x08600000000001BF"
                                },
                                {
                                    "name": "deaths",
                                    "value": 4,
                                    "id": "0x086000000000002A"
                                },
                                {
                                    "name": "eliminations",
                                    "value": 20,
                                    "id": "0x086000000000001F"
                                }
                            ]
                        },
                        {
                            "hero_id": "0x02E0000000000040",
                            "name": "roadhog",
                            "stats": []
                        },
                        {
                            "hero_id": "0x02E000000000013E",
                            "name": "orisa",
                            "stats": [
                                {
                                    "name": "damage",
                                    "value": 2930.042133331299,
                                    "id": "0x08600000000001BF"
                                },
                                {
                                    "name": "deaths",
                                    "value": 2,
                                    "id": "0x086000000000002A"
                                },
                                {
                                    "name": "eliminations",
                                    "value": 5,
                                    "id": "0x086000000000001F"
                                }
                            ]
                        },
                        {
                            "hero_id": "0x02E0000000000007",
                            "name": "reinhardt",
                            "stats": [
                                {
                                    "name": "damage",
                                    "value": 1878,
                                    "id": "0x08600000000001BF"
                                },
                                {
                                    "name": "deaths",
                                    "value": 1,
                                    "id": "0x086000000000002A"
                                },
                                {
                                    "name": "eliminations",
                                    "value": 2,
                                    "id": "0x086000000000001F"
                                }
                            ]
                        },
                        {
                            "hero_id": "0x02E00000000001CA",
                            "name": "wreckingball",
                            "stats": [
                                {
                                    "name": "damage",
                                    "value": 165.33359146118164,
                                    "id": "0x08600000000001BF"
                                },
                                {
                                    "name": "deaths",
                                    "value": 1,
                                    "id": "0x086000000000002A"
                                }
                            ]
                        }
                    ]
                },
                {
                    "esports_player_id": 5442,
                    "stats": [
                        {
                            "name": "damage",
                            "value": 9445.957044661045,
                            "id": "0x08600000000001BF"
                        },
                        {
                            "name": "deaths",
                            "value": 10,
                            "id": "0x086000000000002A"
                        },
                        {
                            "name": "eliminations",
                            "value": 20,
                            "id": "0x086000000000001F"
                        },
                        {
                            "name": "healing",
                            "value": 8217.261046886444,
                            "id": "0x08600000000001C1"
                        }
                    ],
                    "heroes": [
                        {
                            "hero_id": "0x02E0000000000195",
                            "name": "brigitte",
                            "stats": [
                                {
                                    "name": "damage",
                                    "value": 6551.149835944176,
                                    "id": "0x08600000000001BF"
                                },
                                {
                                    "name": "deaths",
                                    "value": 7,
                                    "id": "0x086000000000002A"
                                },
                                {
                                    "name": "eliminations",
                                    "value": 14,
                                    "id": "0x086000000000001F"
                                },
                                {
                                    "name": "healing",
                                    "value": 8217.261046886444,
                                    "id": "0x08600000000001C1"
                                }
                            ]
                        },
                        {
                            "hero_id": "0x02E000000000007A",
                            "name": "dva",
                            "stats": [
                                {
                                    "name": "damage",
                                    "value": 2.4000000953674316,
                                    "id": "0x08600000000001BF"
                                }
                            ]
                        },
                        {
                            "hero_id": "0x02E0000000000003",
                            "name": "tracer",
                            "stats": []
                        },
                        {
                            "hero_id": "0x02E000000000000A",
                            "name": "widowmaker",
                            "stats": [
                                {
                                    "name": "damage",
                                    "value": 2892.407208621502,
                                    "id": "0x08600000000001BF"
                                },
                                {
                                    "name": "deaths",
                                    "value": 3,
                                    "id": "0x086000000000002A"
                                },
                                {
                                    "name": "eliminations",
                                    "value": 6,
                                    "id": "0x086000000000001F"
                                }
                            ]
                        }
                    ]
                },
                {
                    "esports_player_id": 8704,
                    "stats": [
                        {
                            "name": "damage",
                            "value": 18237.07383465767,
                            "id": "0x08600000000001BF"
                        },
                        {
                            "name": "deaths",
                            "value": 7,
                            "id": "0x086000000000002A"
                        },
                        {
                            "name": "eliminations",
                            "value": 28,
                            "id": "0x086000000000001F"
                        }
                    ],
                    "heroes": [
                        {
                            "hero_id": "0x02E0000000000005",
                            "name": "hanzo",
                            "stats": [
                                {
                                    "name": "damage",
                                    "value": 1778.2368240356445,
                                    "id": "0x08600000000001BF"
                                },
                                {
                                    "name": "deaths",
                                    "value": 1,
                                    "id": "0x086000000000002A"
                                },
                                {
                                    "name": "eliminations",
                                    "value": 2,
                                    "id": "0x086000000000001F"
                                }
                            ]
                        },
                        {
                            "hero_id": "0x02E000000000012E",
                            "name": "sombra",
                            "stats": [
                                {
                                    "name": "damage",
                                    "value": 16458.837010622025,
                                    "id": "0x08600000000001BF"
                                },
                                {
                                    "name": "deaths",
                                    "value": 6,
                                    "id": "0x086000000000002A"
                                },
                                {
                                    "name": "eliminations",
                                    "value": 26,
                                    "id": "0x086000000000001F"
                                }
                            ]
                        }
                    ]
                }
            ]
        }
    ],
    "stats": [
        {
            "name": "total_game_time",
            "value": 1200376
        }
    ]
}