{
    "game_id": "matchgame-d91516b9-8fda-d54a-982a-29f77f62fbce",
    "match_id": "match-7123b46b-fbdc-ba42-b14d-983b8edc951f",
    "tournament_id": "tournament-650ec193-0ae6-2c4a-95c6-0296269b3746",
    "tournament_type": "owl",
    "season_id": "2018",
    "game_number": 3,
    "map_id": "0x08000000000000D4",
    "map_type": "HYBRID",
    "esports_tournament_id": 3831,
    "esports_match_id": 10579,
    "teams": [
        {
            "esports_team_id": 4409,
            "stats": [
                {
                    "name": "deaths",
                    "value": 61,
                    "id": "0x086000000000002A"
                }
            ],
            "players": [
                {
                    "esports_player_id": 4647,
                    "stats": [
                        {
                            "name": "damage",
                            "value": 16699.325075149536,
                            "id": "0x08600000000001BF"
                        },
                        {
                            "name": "deaths",
                            "value": 15,
                            "id": "0x086000000000002A"
                        },
                        {
                            "name": "eliminations",
                            "value": 16,
                            "id": "0x086000000000001F"
                        }
                    ],
                    "heroes": [
                        {
                            "hero_id": "0x02E0000000000007",
                            "name": "reinhardt",
                            "stats": [
                                {
                                    "name": "damage",
                                    "value": 16699.325075149536,
                                    "id": "0x08600000000001BF"
                                },
                                {
                                    "name": "deaths",
                                    "value": 15,
                                    "id": "0x086000000000002A"
                                },
                                {
                                    "name": "eliminations",
                                    "value": 16,
                                    "id": "0x086000000000001F"
                                }
                            ]
                        }
                    ]
                },
                {
                    "esports_player_id": 4104,
                    "stats": [
                        {
                            "name": "damage",
                            "value": 12456.815773963928,
                            "id": "0x08600000000001BF"
                        },
                        {
                            "name": "deaths",
                            "value": 10,
                            "id": "0x086000000000002A"
                        },
                        {
                            "name": "eliminations",
                            "value": 20,
                            "id": "0x086000000000001F"
                        },
                        {
                            "name": "healing",
                            "value": 15231.117726802826,
                            "id": "0x08600000000001C1"
                        }
                    ],
                    "heroes": [
                        {
                            "hero_id": "0x02E0000000000079",
                            "name": "lucio",
                            "stats": [
                                {
                                    "name": "damage",
                                    "value": 12456.815773963928,
                                    "id": "0x08600000000001BF"
                                },
                                {
                                    "name": "deaths",
                                    "value": 10,
                                    "id": "0x086000000000002A"
                                },
                                {
                                    "name": "eliminations",
                                    "value": 20,
                                    "id": "0x086000000000001F"
                                },
                                {
                                    "name": "healing",
                                    "value": 15231.117726802826,
                                    "id": "0x08600000000001C1"
                                }
                            ]
                        }
                    ]
                },
                {
                    "esports_player_id": 4638,
                    "stats": [
                        {
                            "name": "damage",
                            "value": 28077.443210601807,
                            "id": "0x08600000000001BF"
                        },
                        {
                            "name": "deaths",
                            "value": 13,
                            "id": "0x086000000000002A"
                        },
                        {
                            "name": "eliminations",
                            "value": 26,
                            "id": "0x086000000000001F"
                        },
                        {
                            "name": "healing",
                            "value": 39.030306935310364,
                            "id": "0x08600000000001C1"
                        }
                    ],
                    "heroes": [
                        {
                            "hero_id": "0x02E000000000006E",
                            "name": "soldier",
                            "stats": [
                                {
                                    "name": "damage",
                                    "value": 230,
                                    "id": "0x08600000000001BF"
                                },
                                {
                                    "name": "deaths",
                                    "value": 1,
                                    "id": "0x086000000000002A"
                                },
                                {
                                    "name": "healing",
                                    "value": 39.030306935310364,
                                    "id": "0x08600000000001C1"
                                }
                            ]
                        },
                        {
                            "hero_id": "0x02E0000000000042",
                            "name": "mccree",
                            "stats": [
                                {
                                    "name": "damage",
                                    "value": 12805.145606994629,
                                    "id": "0x08600000000001BF"
                                },
                                {
                                    "name": "deaths",
                                    "value": 4,
                                    "id": "0x086000000000002A"
                                },
                                {
                                    "name": "eliminations",
                                    "value": 6,
                                    "id": "0x086000000000001F"
                                }
                            ]
                        },
                        {
                            "hero_id": "0x02E0000000000065",
                            "name": "junkrat",
                            "stats": [
                                {
                                    "name": "damage",
                                    "value": 15042.297603607178,
                                    "id": "0x08600000000001BF"
                                },
                                {
                                    "name": "deaths",
                                    "value": 8,
                                    "id": "0x086000000000002A"
                                },
                                {
                                    "name": "eliminations",
                                    "value": 20,
                                    "id": "0x086000000000001F"
                                }
                            ]
                        }
                    ]
                },
                {
                    "esports_player_id": 4098,
                    "stats": [
                        {
                            "name": "damage",
                            "value": 27080.627747774124,
                            "id": "0x08600000000001BF"
                        },
                        {
                            "name": "deaths",
                            "value": 7,
                            "id": "0x086000000000002A"
                        },
                        {
                            "name": "eliminations",
                            "value": 32,
                            "id": "0x086000000000001F"
                        }
                    ],
                    "heroes": [
                        {
                            "hero_id": "0x02E000000000007A",
                            "name": "dva",
                            "stats": [
                                {
                                    "name": "damage",
                                    "value": 2064.4060663580894,
                                    "id": "0x08600000000001BF"
                                },
                                {
                                    "name": "deaths",
                                    "value": 1,
                                    "id": "0x086000000000002A"
                                },
                                {
                                    "name": "eliminations",
                                    "value": 3,
                                    "id": "0x086000000000001F"
                                }
                            ]
                        },
                        {
                            "hero_id": "0x02E0000000000068",
                            "name": "zarya",
                            "stats": [
                                {
                                    "name": "damage",
                                    "value": 25016.221681416035,
                                    "id": "0x08600000000001BF"
                                },
                                {
                                    "name": "deaths",
                                    "value": 6,
                                    "id": "0x086000000000002A"
                                },
                                {
                                    "name": "eliminations",
                                    "value": 29,
                                    "id": "0x086000000000001F"
                                }
                            ]
                        }
                    ]
                },
                {
                    "esports_player_id": 4105,
                    "stats": [
                        {
                            "name": "damage",
                            "value": 8776.185830056667,
                            "id": "0x08600000000001BF"
                        },
                        {
                            "name": "deaths",
                            "value": 9,
                            "id": "0x086000000000002A"
                        },
                        {
                            "name": "eliminations",
                            "value": 29,
                            "id": "0x086000000000001F"
                        },
                        {
                            "name": "healing",
                            "value": 31918.709976553917,
                            "id": "0x08600000000001C1"
                        }
                    ],
                    "heroes": [
                        {
                            "hero_id": "0x02E0000000000005",
                            "name": "hanzo",
                            "stats": []
                        },
                        {
                            "hero_id": "0x02E00000000001A2",
                            "name": "moira",
                            "stats": [
                                {
                                    "name": "damage",
                                    "value": 8776.185830056667,
                                    "id": "0x08600000000001BF"
                                },
                                {
                                    "name": "deaths",
                                    "value": 9,
                                    "id": "0x086000000000002A"
                                },
                                {
                                    "name": "eliminations",
                                    "value": 29,
                                    "id": "0x086000000000001F"
                                },
                                {
                                    "name": "healing",
                                    "value": 31918.709976553917,
                                    "id": "0x08600000000001C1"
                                }
                            ]
                        }
                    ]
                },
                {
                    "esports_player_id": 4642,
                    "stats": [
                        {
                            "name": "damage",
                            "value": 23336.46793267131,
                            "id": "0x08600000000001BF"
                        },
                        {
                            "name": "deaths",
                            "value": 7,
                            "id": "0x086000000000002A"
                        },
                        {
                            "name": "eliminations",
                            "value": 34,
                            "id": "0x086000000000001F"
                        },
                        {
                            "name": "healing",
                            "value": 1268.137631893158,
                            "id": "0x08600000000001C1"
                        }
                    ],
                    "heroes": [
                        {
                            "hero_id": "0x02E0000000000040",
                            "name": "roadhog",
                            "stats": [
                                {
                                    "name": "damage",
                                    "value": 3679.1584362983704,
                                    "id": "0x08600000000001BF"
                                },
                                {
                                    "name": "deaths",
                                    "value": 3,
                                    "id": "0x086000000000002A"
                                },
                                {
                                    "name": "eliminations",
                                    "value": 3,
                                    "id": "0x086000000000001F"
                                },
                                {
                                    "name": "healing",
                                    "value": 1263.587631702423,
                                    "id": "0x08600000000001C1"
                                }
                            ]
                        },
                        {
                            "hero_id": "0x02E000000000007A",
                            "name": "dva",
                            "stats": [
                                {
                                    "name": "damage",
                                    "value": 19657.309496372938,
                                    "id": "0x08600000000001BF"
                                },
                                {
                                    "name": "deaths",
                                    "value": 4,
                                    "id": "0x086000000000002A"
                                },
                                {
                                    "name": "eliminations",
                                    "value": 31,
                                    "id": "0x086000000000001F"
                                },
                                {
                                    "name": "healing",
                                    "value": 4.550000190734863,
                                    "id": "0x08600000000001C1"
                                }
                            ]
                        },
                        {
                            "hero_id": "0x02E000000000000A",
                            "name": "widowmaker",
                            "stats": []
                        }
                    ]
                }
            ]
        },
        {
            "esports_team_id": 4525,
            "stats": [
                {
                    "name": "deaths",
                    "value": 55,
                    "id": "0x086000000000002A"
                }
            ],
            "players": [
                {
                    "esports_player_id": 4136,
                    "stats": [
                        {
                            "name": "damage",
                            "value": 11635.48958748579,
                            "id": "0x08600000000001BF"
                        },
                        {
                            "name": "deaths",
                            "value": 6,
                            "id": "0x086000000000002A"
                        },
                        {
                            "name": "eliminations",
                            "value": 31,
                            "id": "0x086000000000001F"
                        },
                        {
                            "name": "healing",
                            "value": 32052.439824819565,
                            "id": "0x08600000000001C1"
                        }
                    ],
                    "heroes": [
                        {
                            "hero_id": "0x02E00000000001A2",
                            "name": "moira",
                            "stats": [
                                {
                                    "name": "damage",
                                    "value": 8434.266996085644,
                                    "id": "0x08600000000001BF"
                                },
                                {
                                    "name": "deaths",
                                    "value": 4,
                                    "id": "0x086000000000002A"
                                },
                                {
                                    "name": "eliminations",
                                    "value": 28,
                                    "id": "0x086000000000001F"
                                },
                                {
                                    "name": "healing",
                                    "value": 30735.48857009411,
                                    "id": "0x08600000000001C1"
                                }
                            ]
                        },
                        {
                            "hero_id": "0x02E0000000000020",
                            "name": "zenyatta",
                            "stats": [
                                {
                                    "name": "damage",
                                    "value": 3201.2225914001465,
                                    "id": "0x08600000000001BF"
                                },
                                {
                                    "name": "deaths",
                                    "value": 2,
                                    "id": "0x086000000000002A"
                                },
                                {
                                    "name": "eliminations",
                                    "value": 3,
                                    "id": "0x086000000000001F"
                                },
                                {
                                    "name": "healing",
                                    "value": 1316.9512547254562,
                                    "id": "0x08600000000001C1"
                                }
                            ]
                        }
                    ]
                },
                {
                    "esports_player_id": 4138,
                    "stats": [
                        {
                            "name": "damage",
                            "value": 23167.814852684736,
                            "id": "0x08600000000001BF"
                        },
                        {
                            "name": "deaths",
                            "value": 7,
                            "id": "0x086000000000002A"
                        },
                        {
                            "name": "eliminations",
                            "value": 31,
                            "id": "0x086000000000001F"
                        },
                        {
                            "name": "healing",
                            "value": 26.389999866485596,
                            "id": "0x08600000000001C1"
                        }
                    ],
                    "heroes": [
                        {
                            "hero_id": "0x02E000000000007A",
                            "name": "dva",
                            "stats": [
                                {
                                    "name": "damage",
                                    "value": 23167.814852684736,
                                    "id": "0x08600000000001BF"
                                },
                                {
                                    "name": "deaths",
                                    "value": 7,
                                    "id": "0x086000000000002A"
                                },
                                {
                                    "name": "eliminations",
                                    "value": 31,
                                    "id": "0x086000000000001F"
                                },
                                {
                                    "name": "healing",
                                    "value": 26.389999866485596,
                                    "id": "0x08600000000001C1"
                                }
                            ]
                        }
                    ]
                },
                {
                    "esports_player_id": 4623,
                    "stats": [
                        {
                            "name": "damage",
                            "value": 20850.985319137573,
                            "id": "0x08600000000001BF"
                        },
                        {
                            "name": "deaths",
                            "value": 10,
                            "id": "0x086000000000002A"
                        },
                        {
                            "name": "eliminations",
                            "value": 33,
                            "id": "0x086000000000001F"
                        }
                    ],
                    "heroes": [
                        {
                            "hero_id": "0x02E0000000000007",
                            "name": "reinhardt",
                            "stats": [
                                {
                                    "name": "damage",
                                    "value": 15711.85869026184,
                                    "id": "0x08600000000001BF"
                                },
                                {
                                    "name": "deaths",
                                    "value": 8,
                                    "id": "0x086000000000002A"
                                },
                                {
                                    "name": "eliminations",
                                    "value": 25,
                                    "id": "0x086000000000001F"
                                }
                            ]
                        },
                        {
                            "hero_id": "0x02E000000000013E",
                            "name": "orisa",
                            "stats": [
                                {
                                    "name": "damage",
                                    "value": 5139.126628875732,
                                    "id": "0x08600000000001BF"
                                },
                                {
                                    "name": "deaths",
                                    "value": 2,
                                    "id": "0x086000000000002A"
                                },
                                {
                                    "name": "eliminations",
                                    "value": 8,
                                    "id": "0x086000000000001F"
                                }
                            ]
                        },
                        {
                            "hero_id": "0x02E0000000000009",
                            "name": "winston",
                            "stats": []
                        }
                    ]
                },
                {
                    "esports_player_id": 4629,
                    "stats": [
                        {
                            "name": "damage",
                            "value": 24627.02961808443,
                            "id": "0x08600000000001BF"
                        },
                        {
                            "name": "deaths",
                            "value": 9,
                            "id": "0x086000000000002A"
                        },
                        {
                            "name": "eliminations",
                            "value": 31,
                            "id": "0x086000000000001F"
                        }
                    ],
                    "heroes": [
                        {
                            "hero_id": "0x02E0000000000040",
                            "name": "roadhog",
                            "stats": []
                        },
                        {
                            "hero_id": "0x02E0000000000068",
                            "name": "zarya",
                            "stats": [
                                {
                                    "name": "damage",
                                    "value": 19014.618824720383,
                                    "id": "0x08600000000001BF"
                                },
                                {
                                    "name": "deaths",
                                    "value": 8,
                                    "id": "0x086000000000002A"
                                },
                                {
                                    "name": "eliminations",
                                    "value": 24,
                                    "id": "0x086000000000001F"
                                }
                            ]
                        },
                        {
                            "hero_id": "0x02E000000000000A",
                            "name": "widowmaker",
                            "stats": [
                                {
                                    "name": "damage",
                                    "value": 5612.410793364048,
                                    "id": "0x08600000000001BF"
                                },
                                {
                                    "name": "deaths",
                                    "value": 1,
                                    "id": "0x086000000000002A"
                                },
                                {
                                    "name": "eliminations",
                                    "value": 7,
                                    "id": "0x086000000000001F"
                                }
                            ]
                        }
                    ]
                },
                {
                    "esports_player_id": 4625,
                    "stats": [
                        {
                            "name": "damage",
                            "value": 10665.668678760529,
                            "id": "0x08600000000001BF"
                        },
                        {
                            "name": "deaths",
                            "value": 8,
                            "id": "0x086000000000002A"
                        },
                        {
                            "name": "eliminations",
                            "value": 17,
                            "id": "0x086000000000001F"
                        },
                        {
                            "name": "healing",
                            "value": 11515.760434508324,
                            "id": "0x08600000000001C1"
                        }
                    ],
                    "heroes": [
                        {
                            "hero_id": "0x02E0000000000079",
                            "name": "lucio",
                            "stats": [
                                {
                                    "name": "damage",
                                    "value": 10565.668678760529,
                                    "id": "0x08600000000001BF"
                                },
                                {
                                    "name": "deaths",
                                    "value": 7,
                                    "id": "0x086000000000002A"
                                },
                                {
                                    "name": "eliminations",
                                    "value": 17,
                                    "id": "0x086000000000001F"
                                },
                                {
                                    "name": "healing",
                                    "value": 9200.825374364853,
                                    "id": "0x08600000000001C1"
                                }
                            ]
                        },
                        {
                            "hero_id": "0x02E0000000000004",
                            "name": "mercy",
                            "stats": [
                                {
                                    "name": "damage",
                                    "value": 100,
                                    "id": "0x08600000000001BF"
                                },
                                {
                                    "name": "deaths",
                                    "value": 1,
                                    "id": "0x086000000000002A"
                                },
                                {
                                    "name": "healing",
                                    "value": 2314.9350601434708,
                                    "id": "0x08600000000001C1"
                                }
                            ]
                        }
                    ]
                },
                {
                    "esports_player_id": 4140,
                    "stats": [
                        {
                            "name": "damage",
                            "value": 32519.891995429993,
                            "id": "0x08600000000001BF"
                        },
                        {
                            "name": "deaths",
                            "value": 15,
                            "id": "0x086000000000002A"
                        },
                        {
                            "name": "eliminations",
                            "value": 32,
                            "id": "0x086000000000001F"
                        }
                    ],
                    "heroes": [
                        {
                            "hero_id": "0x02E000000000006E",
                            "name": "soldier",
                            "stats": []
                        },
                        {
                            "hero_id": "0x02E0000000000065",
                            "name": "junkrat",
                            "stats": [
                                {
                                    "name": "damage",
                                    "value": 32519.891995429993,
                                    "id": "0x08600000000001BF"
                                },
                                {
                                    "name": "deaths",
                                    "value": 15,
                                    "id": "0x086000000000002A"
                                },
                                {
                                    "name": "eliminations",
                                    "value": 32,
                                    "id": "0x086000000000001F"
                                }
                            ]
                        }
                    ]
                }
            ]
        }
    ],
    "stats": [
        {
            "name": "total_game_time",
            "value": 1158315
        }
    ]
}